fwdi/Application/__init__.py
fwdi/Application/dependency_injection.py
fwdi/Application/Abstractions/__init__.py
fwdi/Application/Abstractions/base_broker_client.py
fwdi/Application/Abstractions/base_controller.py
fwdi/Application/Abstractions/base_data_store.py
fwdi/Application/Abstractions/base_di_container.py
fwdi/Application/Abstractions/base_gradio_request.py
fwdi/Application/Abstractions/base_hash_token_config.py
fwdi/Application/Abstractions/base_http_auth.py
fwdi/Application/Abstractions/base_jwt_service.py
fwdi/Application/Abstractions/base_jwt_service_instance.py
fwdi/Application/Abstractions/base_jwt_tools_v2.py
fwdi/Application/Abstractions/base_logging.py
fwdi/Application/Abstractions/base_manager_context.py
fwdi/Application/Abstractions/base_manager_mcp_service.py
fwdi/Application/Abstractions/base_mcp_client.py
fwdi/Application/Abstractions/base_mcp_service.py
fwdi/Application/Abstractions/base_panel.py
fwdi/Application/Abstractions/base_rest_client.py
fwdi/Application/Abstractions/base_service_collection.py
fwdi/Application/Abstractions/base_similarity_data_store.py
fwdi/Application/Abstractions/base_task_callback_handler.py
fwdi/Application/Abstractions/base_task_handler.py
fwdi/Application/Abstractions/base_task_job_check.py
fwdi/Application/Abstractions/base_task_queue_manager.py
fwdi/Application/Abstractions/base_user_repository.py
fwdi/Application/Abstractions/base_web_main_page.py
fwdi/Application/Abstractions/base_web_tab_item.py
fwdi/Application/Abstractions/base_web_tabs_panel.py
fwdi/Application/Abstractions/db_context.py
fwdi/Application/Abstractions/meta_service.py
fwdi/Application/Abstractions/routeble.py
fwdi/Application/Abstractions/service_descriptor.py
fwdi/Application/Abstractions/Core/base_controller.py
fwdi/Application/Abstractions/Core/base_di_container.py
fwdi/Application/Abstractions/Core/base_gradio_request.py
fwdi/Application/Abstractions/Core/base_hash_token_config.py
fwdi/Application/Abstractions/Core/base_http_auth.py
fwdi-0.3.39.dist-info/METADATA
fwdi-0.3.39.dist-info/WHEEL
fwdi-0.3.39.dist-info/licenses/LICENSE
fwdi-0.3.39.dist-info/RECORD
