Metadata-Version: 2.4
Name: fwdi
Version: 0.3.39
Summary: Solve Flat Web library With Lightweight Dependency injection Container
Project-URL: Homepage, https://github.com/Alitrix/fwdi-dev
Project-URL: Issues, https://github.com/Alitrix/fwdi-dev/issues
Author-email: Pozin Andrey <alien-kms@mail.ru>
License-File: LICENSE
Classifier: Development Status :: 3 - Alpha
Classifier: Intended Audience :: Developers
Classifier: License :: OSI Approved :: MIT License
Classifier: Operating System :: OS Independent
Classifier: Programming Language :: Python :: 3.10
Classifier: Topic :: Software Development
Requires-Python: >=3.10
Requires-Dist: elasticsearch
Requires-Dist: fastapi
Requires-Dist: fastapi-jsonrpc
Requires-Dist: fastapi-websocket-rpc
Requires-Dist: fastmcp
Requires-Dist: gradio
Requires-Dist: itsdangerous
Requires-Dist: json-repair
Requires-Dist: passlib
Requires-Dist: peewee
Requires-Dist: pika
Requires-Dist: psutil
Requires-Dist: pyjwt
Requires-Dist: python-json-logger
Requires-Dist: python-logstash
Requires-Dist: python-multipart
Requires-Dist: requests
Requires-Dist: uvicorn
Requires-Dist: websockets
